main.py
mcp_weather_upload-0.1.4.dist-info/METADATA
mcp_weather_upload-0.1.4.dist-info/WHEEL
mcp_weather_upload-0.1.4.dist-info/entry_points.txt
mcp_weather_upload-0.1.4.dist-info/top_level.txt
mcp_weather_upload-0.1.4.dist-info/RECORD
