Metadata-Version: 2.4
Name: mcp-weather-upload
Version: 0.1.4
Summary: 输入OpenWeather-API-KEY，获取天气信息。
Requires-Python: >=3.12
Requires-Dist: build>=1.3.0
Requires-Dist: httpx>=0.28.1
Requires-Dist: mcp>=1.17.0
Requires-Dist: twine>=6.2.0
